GraficaWithGamba/__init__.py
GraficaWithGamba/grafica.py
GraficaWithGamba-1.0.1.dist-info/LICENSE
GraficaWithGamba-1.0.1.dist-info/METADATA
GraficaWithGamba-1.0.1.dist-info/WHEEL
GraficaWithGamba-1.0.1.dist-info/top_level.txt
GraficaWithGamba-1.0.1.dist-info/RECORD
